spidermonkey-48.0a2.dist-info/RECORD
spidermonkey-48.0a2.dist-info/WHEEL
spidermonkey-48.0a2.dist-info/top_level.txt
spidermonkey-48.0a2.dist-info/pbr.json
spidermonkey-48.0a2.dist-info/METADATA
spidermonkey-48.0a2.dist-info/DESCRIPTION.rst
spidermonkey-48.0a2.dist-info/metadata.json
spidermonkey-48.0a2.data/purelib/spidermonkey/__init__.py
spidermonkey-48.0a2.data/purelib/spidermonkey/lib/os-x/libnss3.dylib
spidermonkey-48.0a2.data/purelib/spidermonkey/lib/os-x/js
spidermonkey-48.0a2.data/purelib/spidermonkey/lib/os-x/libmozglue.dylib
