Metadata-Version: 2.0
Name: spidermonkey
Version: 48.0a2
Summary: A standalone executable Spidermonkey JavaScript shell, and a Python utility module to run it.
Home-page: https://github.com/kmaglione/python-spidermonkey/
Author: Mozilla Corporation
Author-email: addons-team@mozilla.com
License: MPLv2
Platform: linux-x86_64
Platform: macos-10.10-intel
Classifier: Development Status :: 4 - Beta
Classifier: Intended Audience :: Developers
Classifier: License :: OSI Approved :: Mozilla Public License 2.0 (MPL 2.0)
Classifier: Topic :: Software Development :: Libraries :: Python Modules
Requires-Dist: setuptools
